sphinxcontrib/__init__.py
sphinxcontrib/traceables/__init__.py
sphinxcontrib/traceables/filter.py
sphinxcontrib/traceables/graph.py
sphinxcontrib/traceables/infrastructure.py
sphinxcontrib/traceables/matrix.py
sphinxcontrib/traceables/traceables.py
sphinxcontrib/traceables/static/traceables-matrix.css
sphinxcontrib_traceables-0.1.4.dist-info/top_level.txt
sphinxcontrib_traceables-0.1.4.dist-info/METADATA
sphinxcontrib_traceables-0.1.4.dist-info/DESCRIPTION.rst
sphinxcontrib_traceables-0.1.4.dist-info/metadata.json
sphinxcontrib_traceables-0.1.4.dist-info/WHEEL
sphinxcontrib_traceables-0.1.4.dist-info/RECORD
