Metadata-Version: 2.0
Name: sphinxcontrib-traceables
Version: 0.1.4
Summary: Sphinx extension that adds traceability within documentation
Home-page: https://github.com/t4ngo/sphinxcontrib-traceables
Author: Christo Butcher
Author-email: UNKNOWN
License: Apache 2.0
Platform: any
Classifier: Development Status :: 3 - Alpha
Classifier: Environment :: Other Environment
Classifier: Environment :: Plugins
Classifier: Framework :: Sphinx :: Extension
Classifier: Intended Audience :: Developers
Classifier: Intended Audience :: Information Technology
Classifier: Intended Audience :: Science/Research
Classifier: Intended Audience :: System Administrators
Classifier: License :: OSI Approved :: Apache Software License
Classifier: Natural Language :: English
Classifier: Operating System :: OS Independent
Classifier: Programming Language :: Python
Classifier: Topic :: Software Development :: Documentation
Classifier: Topic :: Software Development :: Libraries :: Python Modules
Requires-Dist: Sphinx (>=1.3)
Requires-Dist: graphviz (>=0.4.6)
